jasmin/__init__.py
jasmin/bin/__init__.py
jasmin/bin/dlrd.py
jasmin/bin/dlrlookupd.py
jasmin/bin/interceptord.py
jasmin/bin/jasmind.py
jasmin/config/__init__.py
jasmin/interceptor/__init__.py
jasmin/interceptor/configs.py
jasmin/interceptor/interceptor.py
jasmin/interceptor/proxies.py
jasmin/managers/__init__.py
jasmin/managers/clients.py
jasmin/managers/configs.py
jasmin/managers/content.py
jasmin/managers/dlr.py
jasmin/managers/listeners.py
jasmin/managers/proxies.py
jasmin/protocols/__init__.py
jasmin/protocols/validation.py
jasmin/protocols/cli/__init__.py
jasmin/protocols/cli/configs.py
jasmin/protocols/cli/factory.py
jasmin/protocols/cli/filtersm.py
jasmin/protocols/cli/groupsm.py
jasmin/protocols/cli/httpccm.py
jasmin/protocols/cli/jcli.py
jasmin/protocols/cli/managers.py
jasmin/protocols/cli/mointerceptorm.py
jasmin/protocols/cli/morouterm.py
jasmin/protocols/cli/mtinterceptorm.py
jasmin/protocols/cli/mtrouterm.py
jasmin/protocols/cli/options.py
jasmin/protocols/cli/protocol.py
jasmin/protocols/cli/smppccm.py
jasmin/protocols/cli/statsm.py
jasmin/protocols/cli/usersm.py
jasmin/protocols/http/__init__.py
jasmin/protocols/http/configs.py
jasmin/protocols/http/errors.py
jasmin/protocols/http/server.py
jasmin/protocols/http/stats.py
jasmin/protocols/http/validation.py
jasmin/protocols/http/endpoints/__init__.py
jasmin/protocols/http/endpoints/balance.py
jasmin/protocols/http/endpoints/ping.py
jasmin/protocols/http/endpoints/rate.py
jasmin/protocols/http/endpoints/send.py
jasmin/protocols/rest/__init__.py
jasmin/protocols/rest/api.py
jasmin/protocols/rest/config.py
jasmin/protocols/rest/tasks.py
jasmin/protocols/smpp/__init__.py
jasmin/protocols/smpp/configs.py
jasmin/protocols/smpp/error.py
jasmin/protocols/smpp/factory.py
jasmin/protocols/smpp/operations.py
jasmin/protocols/smpp/pb.py
jasmin/protocols/smpp/protocol.py
jasmin/protocols/smpp/proxies.py
jasmin/protocols/smpp/services.py
jasmin/protocols/smpp/stats.py
jasmin/protocols/smpp/validation.py
jasmin-0.10.6.dist-info/LICENSE
jasmin-0.10.6.dist-info/METADATA
jasmin-0.10.6.dist-info/WHEEL
jasmin-0.10.6.dist-info/top_level.txt
jasmin-0.10.6.dist-info/RECORD
