Metadata-Version: 2.1
Name: jasmin
Version: 0.10.6
Summary: Jasmin is a very complete open source SMS Gateway with many enterprise-class features.
Home-page: https://www.jasminsms.com
Author: Jookies LTD
Author-email: jasmin@jookies.net
License: Apache v2.0
Keywords: jasmin,sms,messaging,smpp,smsc,smsgateway
Platform: POSIX
Classifier: Development Status :: 5 - Production/Stable
Classifier: Framework :: Twisted
Classifier: Intended Audience :: Developers
Classifier: License :: OSI Approved :: Apache Software License
Classifier: Operating System :: POSIX
Classifier: Programming Language :: Python :: 3 :: Only
Classifier: Programming Language :: Python :: 3
Classifier: Topic :: Software Development :: Libraries :: Python Modules
Classifier: Topic :: System :: Networking
Classifier: Topic :: Communications
Classifier: Topic :: Communications :: Telephony
Requires-Dist: pyasn1 (~=0.4.8)
Requires-Dist: pyOpenSSL (~=19.1.0)
Requires-Dist: Twisted (~=20.3.0)
Requires-Dist: treq (~=20.3.0)
Requires-Dist: pyparsing (~=2.4.7)
Requires-Dist: python-dateutil (~=2.8.1)
Requires-Dist: service-identity (~=18.1.0)
Requires-Dist: lockfile (~=0.12.2)
Requires-Dist: falcon (~=2.0.0)
Requires-Dist: txredisapi (~=1.4.7)
Requires-Dist: tabulate (~=0.8.7)
Requires-Dist: txAMQP3 (~=0.9.0)
Requires-Dist: smpp.pdu3 (~=0.4)
Requires-Dist: smpp.twisted3 (~=0.6)
Requires-Dist: python-messaging (~=0.5.13)
Requires-Dist: celery (>=4.0.0)
Requires-Dist: redis (~=3.4.1)
Requires-Dist: requests (~=2.23.0)
Requires-Dist: python-mimeparse (~=1.6.0)
